encoder7/__init__.py
encoder7/common.py
encoder7/encode.py
encoder7/encoder7.py
encoder7-1.0.1.dist-info/LICENSE
encoder7-1.0.1.dist-info/METADATA
encoder7-1.0.1.dist-info/WHEEL
encoder7-1.0.1.dist-info/entry_points.txt
encoder7-1.0.1.dist-info/top_level.txt
encoder7-1.0.1.dist-info/RECORD
