Metadata-Version: 2.1
Name: encoder7
Version: 1.0.1
Summary: Python Boilerplate contains all the boilerplate you need to create a Python package.
Author-email: Kanishk mittal <kanishkmittal2005@gmail.com>
License: MIT License
Project-URL: Homepage, https://github.com/Kanishk-mittal/encoder7
Keywords: encoder7
Classifier: Intended Audience :: Developers
Classifier: License :: OSI Approved :: MIT License
Classifier: Natural Language :: English
Classifier: Programming Language :: Python :: 3.8
Classifier: Programming Language :: Python :: 3.9
Classifier: Programming Language :: Python :: 3.10
Classifier: Programming Language :: Python :: 3.11
Classifier: Programming Language :: Python :: 3.12
Requires-Python: >=3.8
License-File: LICENSE
Requires-Dist: numpy
Provides-Extra: all
Requires-Dist: encoder7[extra] ; extra == 'all'
Provides-Extra: extra
Requires-Dist: pandas ; extra == 'extra'
